pytest_datadir/__init__.py
pytest_datadir/_version.py
pytest_datadir/plugin.py
pytest_datadir/py.typed
pytest_datadir-1.7.2.dist-info/licenses/AUTHORS
pytest_datadir-1.7.2.dist-info/licenses/LICENSE
pytest_datadir-1.7.2.dist-info/METADATA
pytest_datadir-1.7.2.dist-info/WHEEL
pytest_datadir-1.7.2.dist-info/entry_points.txt
pytest_datadir-1.7.2.dist-info/top_level.txt
pytest_datadir-1.7.2.dist-info/RECORD
