Metadata-Version: 2.4
Name: pytest-datadir
Version: 1.7.2
Summary: pytest plugin for test data directories and files
Author-email: Gabriel Reis <gabrielcnr@gmail.com>
License: MIT
Project-URL: Homepage, http://github.com/gabrielcnr/pytest-datadir
Keywords: pytest,test,unittest,directory,file
Classifier: Development Status :: 5 - Production/Stable
Classifier: Intended Audience :: Developers
Classifier: License :: OSI Approved :: MIT License
Classifier: Operating System :: OS Independent
Classifier: Programming Language :: Python :: 3.8
Classifier: Programming Language :: Python :: 3.9
Classifier: Programming Language :: Python :: 3.10
Classifier: Programming Language :: Python :: 3.11
Classifier: Programming Language :: Python :: 3.12
Classifier: Topic :: Software Development :: Quality Assurance
Classifier: Topic :: Software Development :: Testing
Requires-Python: >=3.8
License-File: LICENSE
License-File: AUTHORS
Requires-Dist: pytest>=7.0
Provides-Extra: testing
Requires-Dist: pytest; extra == "testing"
Requires-Dist: tox; extra == "testing"
Provides-Extra: dev
Requires-Dist: pytest-datadir[testing]; extra == "dev"
Requires-Dist: pre-commit; extra == "dev"
Dynamic: license-file
